minedatabase/__init__.py
minedatabase/compound_io.py
minedatabase/databases.py
minedatabase/metabolomics.py
minedatabase/pickaxe.py
minedatabase/reactions.py
minedatabase/rules.py
minedatabase/thermodynamics.py
minedatabase/utils.py
minedatabase/NP_Score/__init__.py
minedatabase/NP_Score/npscorer.py
minedatabase/NP_Score/publicnp.model.gz
minedatabase/filters/__init__.py
minedatabase/filters/base_filter.py
minedatabase/filters/feasibility.py
minedatabase/filters/metabolomics.py
minedatabase/filters/property.py
minedatabase/filters/similarity.py
minedatabase/filters/thermodynamics.py
tests/test_unit/__init__.py
tests/test_unit/test_databases.py
tests/test_unit/test_feas.py
tests/test_unit/test_filters.py
tests/test_unit/test_metabolomics.py
tests/test_unit/test_pickaxe.py
tests/test_unit/test_rules.py
tests/test_unit/test_thermodynamics.py
tests/test_unit/test_utils.py
minedatabase-2.2.0.dist-info/LICENSE
minedatabase-2.2.0.dist-info/METADATA
minedatabase-2.2.0.dist-info/WHEEL
minedatabase-2.2.0.dist-info/top_level.txt
minedatabase-2.2.0.dist-info/RECORD
