Metadata-Version: 2.1
Name: minedatabase
Version: 2.2.0
Summary: Metabolic In silico Network Expansions
Home-page: https://github.com/tyo-nu/MINE-Database
Author: Kevin Shebek, Jonathan Strutz
Author-email: jonstrutz11@gmail.com
License: MIT
Classifier: Development Status :: 5 - Production/Stable
Classifier: Intended Audience :: Science/Research
Classifier: License :: OSI Approved :: MIT License
Classifier: Topic :: Scientific/Engineering :: Bio-Informatics
Classifier: Topic :: Scientific/Engineering :: Chemistry
Classifier: Programming Language :: Python :: 3.7
Classifier: Programming Language :: Python :: 3.9
Classifier: Programming Language :: Python :: 3.8
Requires-Python: <3.10,>=3.7
License-File: LICENSE
Requires-Dist: keras
Requires-Dist: python-libsbml
Requires-Dist: lxml (==4.9)
Requires-Dist: mordred (==1.2)
Requires-Dist: pandas
Requires-Dist: pymongo
Requires-Dist: rdkit
Requires-Dist: scikit-learn
Provides-Extra: test
Requires-Dist: pytest ; extra == 'test'
